statsig_ai/__init__.py
statsig_ai/ai_eval_grade_data.py
statsig_ai/prompt.py
statsig_ai/prompt_version.py
statsig_ai/py.typed
statsig_ai/statsig_ai.py
statsig_ai/statsig_ai_base.py
statsig_ai/version.py
statsig_ai/evals/__init__.py
statsig_ai/evals/eval.py
statsig_ai/evals/eval_types.py
statsig_ai/evals/serializable_data_class.py
statsig_ai/otel/__init__.py
statsig_ai/otel/conventions.py
statsig_ai/otel/exporter.py
statsig_ai/otel/otel.py
statsig_ai/otel/processor.py
statsig_ai/otel/singleton.py
statsig_ai/wrappers/__init__.py
statsig_ai/wrappers/configs.py
statsig_ai/wrappers/genai_attribute_helper.py
statsig_ai/wrappers/openai.py
statsig_ai/wrappers/openai_impl.py
statsig_ai/wrappers/span_telemetry.py
statsig_ai-0.0.1b8.dist-info/licenses/LICENSE
statsig_ai-0.0.1b8.dist-info/METADATA
statsig_ai-0.0.1b8.dist-info/WHEEL
statsig_ai-0.0.1b8.dist-info/top_level.txt
statsig_ai-0.0.1b8.dist-info/RECORD
