Metadata-Version: 2.4
Name: statsig_ai
Version: 0.0.1b8
Summary: Statsig AI Python SDK
Home-page: https://github.com/statsig-io/statsig-ai-python
Author: 
Author-email: 
License: ISC
Classifier: Intended Audience :: Developers
Classifier: Programming Language :: Python
Classifier: Programming Language :: Python :: 3
Classifier: Topic :: Software Development :: Libraries :: Python Modules
Requires-Python: >=3.9
License-File: LICENSE
Requires-Dist: requests
Requires-Dist: statsig-python-core
Requires-Dist: opentelemetry-api
Requires-Dist: opentelemetry-sdk
Requires-Dist: opentelemetry-exporter-otlp-proto-http
Requires-Dist: typing-extensions>=4.1.0
Requires-Dist: tqdm
Provides-Extra: test
Requires-Dist: pytest; extra == "test"
Requires-Dist: pytest-httpserver; extra == "test"
Requires-Dist: werkzeug; extra == "test"
Requires-Dist: statsig-python-core; extra == "test"
Requires-Dist: pytest-asyncio; extra == "test"
Requires-Dist: openai; extra == "test"
Dynamic: classifier
Dynamic: description
Dynamic: description-content-type
Dynamic: home-page
Dynamic: license
Dynamic: license-file
Dynamic: provides-extra
Dynamic: requires-dist
Dynamic: requires-python
Dynamic: summary
